catalystcoop_pudl-2025.12.1.dist-info/licenses/LICENSE.txt
pudl/__init__.py
pudl/__main__.py
pudl/dbt_wrapper.py
pudl/helpers.py
pudl/io_managers.py
pudl/logging_helpers.py
pudl/resources.py
pudl/settings.py
pudl/validate.py
pudl/analysis/__init__.py
pudl/analysis/allocate_gen_fuel.py
pudl/analysis/fuel_by_plant.py
pudl/analysis/mcoe.py
pudl/analysis/plant_parts_eia.py
pudl/analysis/service_territory.py
pudl/analysis/spatial.py
pudl/analysis/state_demand.py
pudl/analysis/timeseries_cleaning.py
pudl/analysis/timeseries_evaluation.py
pudl/analysis/ml_tools/__init__.py
pudl/analysis/ml_tools/experiment_tracking.py
pudl/analysis/ml_tools/models.py
pudl/analysis/record_linkage/__init__.py
pudl/analysis/record_linkage/classify_plants_ferc1.py
pudl/analysis/record_linkage/eia_ferc1_inputs.py
pudl/analysis/record_linkage/eia_ferc1_model_config.py
pudl/analysis/record_linkage/eia_ferc1_record_linkage.py
pudl/analysis/record_linkage/eia_ferc1_train.py
pudl/analysis/record_linkage/embed_dataframe.py
pudl/analysis/record_linkage/link_cross_year.py
pudl/analysis/record_linkage/name_cleaner.py
pudl/convert/__init__.py
pudl/convert/censusdp1tract_to_sqlite.py
pudl/convert/metadata_to_rst.py
pudl/etl/__init__.py
pudl/etl/asset_checks.py
pudl/etl/check_foreign_keys.py
pudl/etl/cli.py
pudl/etl/eia_bulk_elec_assets.py
pudl/etl/glue_assets.py
pudl/etl/static_assets.py
pudl/extract/__init__.py
pudl/extract/censuspep.py
pudl/extract/csv.py
pudl/extract/dbf.py
pudl/extract/eia176.py
pudl/extract/eia191.py
pudl/extract/eia757a.py
pudl/extract/eia860.py
pudl/extract/eia860m.py
pudl/extract/eia861.py
pudl/extract/eia923.py
pudl/extract/eia930.py
pudl/extract/eiaaeo.py
pudl/extract/eiaapi.py
pudl/extract/epacems.py
pudl/extract/excel.py
pudl/extract/extractor.py
pudl/extract/ferc.py
pudl/extract/ferc1.py
pudl/extract/ferc2.py
pudl/extract/ferc6.py
pudl/extract/ferc60.py
pudl/extract/ferc714.py
pudl/extract/gridpathratoolkit.py
pudl/extract/nrelatb.py
pudl/extract/parquet.py
pudl/extract/phmsagas.py
pudl/extract/sec10k.py
pudl/extract/vcerare.py
catalystcoop_pudl-2025.12.1.dist-info/METADATA
catalystcoop_pudl-2025.12.1.dist-info/WHEEL
catalystcoop_pudl-2025.12.1.dist-info/entry_points.txt
catalystcoop_pudl-2025.12.1.dist-info/top_level.txt
catalystcoop_pudl-2025.12.1.dist-info/RECORD
