Metadata-Version: 2.4
Name: catalystcoop.pudl
Version: 2025.12.1
Summary: An open data processing pipeline for US energy data
Author-email: Catalyst Cooperative <pudl@catalyst.coop>
License: Copyright 2017-2022 Catalyst Cooperative
Project-URL: Homepage, https://catalyst.coop/pudl/
Project-URL: Source, https://github.com/catalyst-cooperative/pudl
Project-URL: Documentation, https://catalystcoop-pudl.readthedocs.io
Project-URL: Release Notes, https://catalystcoop-pudl.readthedocs.io/en/nightly/release_notes.html
Project-URL: Issue Tracker, https://github.com/catalyst-cooperative/pudl/issues
Project-URL: Support, https://github.com/catalyst-cooperative/pudl/discussions
Project-URL: Funding, https://catalyst.coop/support-the-pudl-project/
Keywords: analysis,climate change,coal,data,economics,eia 860,eia 861,eia 923,electricity,emissions,energy,epa ampd,epa cems,ferc form 1,ferc form 2,ferc form 6,ferc form 60,ferc form 714,finance,fossil fuel,natural gas,oil,policy,utility
Classifier: Development Status :: 5 - Production/Stable
Classifier: Environment :: Console
Classifier: Intended Audience :: Science/Research
Classifier: License :: OSI Approved :: MIT License
Classifier: Natural Language :: English
Classifier: Operating System :: OS Independent
Classifier: Programming Language :: Python :: 3 :: Only
Classifier: Programming Language :: Python :: 3.13
Classifier: Programming Language :: Python :: 3
Classifier: Programming Language :: Python
Classifier: Topic :: Scientific/Engineering
Requires-Python: <3.14.0a0,>=3.13
License-File: LICENSE.txt
Requires-Dist: alembic>=1.17
Requires-Dist: boto3>=1.35
Requires-Dist: bottleneck>=1.5.0
Requires-Dist: build>=1.2
Requires-Dist: catalystcoop.dbfread<3.1,>=3.0
Requires-Dist: catalystcoop.ferc-xbrl-extractor<2,>=1.7.3
Requires-Dist: click<8.2.0,>=8
Requires-Dist: coloredlogs>=14.0
Requires-Dist: conda-lock>=3
Requires-Dist: coverage>=7.10
Requires-Dist: dagster>=1.12.1
Requires-Dist: dagster-dbt
Requires-Dist: dagster-postgres
Requires-Dist: dbt-core>=1.10.13
Requires-Dist: dbt-duckdb>=1.9.4
Requires-Dist: deepdiff>=8
Requires-Dist: doc8>=1.1
Requires-Dist: duckdb>=1.4
Requires-Dist: email-validator>=1.0.3
Requires-Dist: frictionless<6,>=5
Requires-Dist: fsspec>=2025
Requires-Dist: furo>=2024
Requires-Dist: gcsfs>=2025
Requires-Dist: gdal==3.12.0
Requires-Dist: geopandas>=1.1
Requires-Dist: geoarrow-pyarrow>=0.2
Requires-Dist: grpcio==1.73.1
Requires-Dist: grpcio-health-checking==1.73.1
Requires-Dist: grpcio-status==1.73.1
Requires-Dist: hypothesis>=6.123
Requires-Dist: jellyfish>=1
Requires-Dist: jinja2>=3.1
Requires-Dist: jupyter
Requires-Dist: matplotlib>=3.10
Requires-Dist: mlflow>=3.6
Requires-Dist: nbconvert>=7
Requires-Dist: nbformat>=5.10
Requires-Dist: networkx>=3.6
Requires-Dist: numba>=0.62
Requires-Dist: numexpr>=2.10
Requires-Dist: numpy>=2.3
Requires-Dist: packaging>=25
Requires-Dist: pandas>=2.3
Requires-Dist: pandera>=0.27
Requires-Dist: polars>=1.35
Requires-Dist: pre-commit>=4
Requires-Dist: pyarrow<21,>=20
Requires-Dist: pydantic>=2.12
Requires-Dist: pydantic-settings>=2.11
Requires-Dist: pytest>=9
Requires-Dist: pytest-console-scripts>=1.4
Requires-Dist: pytest-cov>=7
Requires-Dist: pytest-mock>=3.15
Requires-Dist: pytest-order>=1.3
Requires-Dist: pytest-xdist>=3.8
Requires-Dist: python-calamine>=0.6.1
Requires-Dist: python-dotenv>=1
Requires-Dist: pytz>=2025
Requires-Dist: pyyaml>=6
Requires-Dist: readthedocs-sphinx-ext>=2
Requires-Dist: requests>=2.32
Requires-Dist: responses>=0.25
Requires-Dist: ruff>=0.14
Requires-Dist: s3fs>=2025
Requires-Dist: scikit-learn>=1.7
Requires-Dist: scipy>=1.16
Requires-Dist: Shapely>=2.1.1
Requires-Dist: splink>=4.0.10
Requires-Dist: sphinx>=8
Requires-Dist: sphinx-autoapi>=3.6.1
Requires-Dist: sphinx-issues>=5
Requires-Dist: sphinx-reredirects>=1
Requires-Dist: sphinx-tabs>=3.4
Requires-Dist: sphinxcontrib_bibtex>=2.6
Requires-Dist: sphinxcontrib_googleanalytics>=0.4
Requires-Dist: sqlalchemy>=2
Requires-Dist: timezonefinder>=8
Requires-Dist: typos>=1.39
Requires-Dist: universal_pathlib>=0.2
Requires-Dist: urllib3>=2.4
Requires-Dist: xlsxwriter>=3.2
Provides-Extra: dev
Requires-Dist: dagster-webserver>=1.12.1; extra == "dev"
Requires-Dist: jupyterlab>4.4; extra == "dev"
Requires-Dist: jupyter-lsp; extra == "dev"
Requires-Dist: jupyterlab-lsp; extra == "dev"
Requires-Dist: memray>=1.18.0; extra == "dev"
Requires-Dist: ruff-lsp; extra == "dev"
Requires-Dist: jupyter-resource-usage; extra == "dev"
Requires-Dist: pygraphviz; extra == "dev"
Requires-Dist: terraform>=1.13; extra == "dev"
Dynamic: license-file
